LICENSE
README.md
setup.py
lib/ibm_flask_jwt/__init__.py
lib/ibm_flask_jwt/auth_props.py
lib/ibm_flask_jwt/decorators.py
lib/ibm_flask_jwt.egg-info/PKG-INFO
lib/ibm_flask_jwt.egg-info/SOURCES.txt
lib/ibm_flask_jwt.egg-info/dependency_links.txt
lib/ibm_flask_jwt.egg-info/requires.txt
lib/ibm_flask_jwt.egg-info/top_level.txt